Spruce_collections-0.2.3-py2.7-nspkg.pth
spruce/collections/_exc.py
spruce/collections/__init__.py
spruce/collections/_mappings/__init__.py
spruce/collections/_mappings/_misc.py
spruce/collections/_sets/__init__.py
spruce/collections/_sets/_universalizable.py
spruce/collections/_sets/_misc.py
spruce/collections/_sequences/__init__.py
Spruce_collections-0.2.3.dist-info/METADATA
Spruce_collections-0.2.3.dist-info/entry_points.txt
Spruce_collections-0.2.3.dist-info/RECORD
Spruce_collections-0.2.3.dist-info/top_level.txt
Spruce_collections-0.2.3.dist-info/namespace_packages.txt
Spruce_collections-0.2.3.dist-info/WHEEL
Spruce_collections-0.2.3.dist-info/metadata.json
Spruce_collections-0.2.3.dist-info/DESCRIPTION.rst
