Metadata-Version: 2.0
Name: Spruce-collections
Version: 0.2.3
Summary: Container data types
Home-page: UNKNOWN
Author: Ivan D Vasin
Author-email: nisavid@gmail.com
License: GNU LESSER GENERAL PUBLIC LICENSE
Requires-Dist: multimap
Requires-Dist: oset
Requires-Dist: spruce-types
